{
  "scraped_at": "2026-03-07T23:42:54.285905+00:00",
  "source_url": "https://glint.trade/feed",
  "item_count": 1,
  "items": [
    {
      "countries": [
        {
          "count": 179,
          "country": "IR",
          "recent": 8,
          "volume": 676721100.3013941
        },
        {
          "count": 165,
          "country": "US",
          "recent": 16,
          "volume": 423490363.50688577
        },
        {
          "count": 110,
          "country": "IL",
          "recent": 4,
          "volume": 629252446.7380652
        },
        {
          "count": 59,
          "country": "LB",
          "recent": 5,
          "volume": 24530118.00733904
        },
        {
          "count": 49,
          "country": "UA",
          "recent": 3,
          "volume": 1427714615.6874926
        },
        {
          "count": 21,
          "country": "BH",
          "recent": 8,
          "volume": 21293420.411342
        },
        {
          "count": 15,
          "country": "SA",
          "recent": 0,
          "volume": 7510633.89050901
        },
        {
          "count": 14,
          "country": "IQ",
          "recent": 0,
          "volume": 14531740.614261458
        },
        {
          "count": 13,
          "country": "KW",
          "recent": 7,
          "volume": 28380708.250149056
        },
        {
          "count": 12,
          "country": "RU",
          "recent": 1,
          "volume": 147835123.94235492
        },
        {
          "count": 11,
          "country": "AE",
          "recent": 0,
          "volume": 23440073.242126655
        },
        {
          "count": 8,
          "country": "GB",
          "recent": 1,
          "volume": 46468126.606645495
        },
        {
          "count": 6,
          "country": "AZ",
          "recent": 0,
          "volume": 29596036.865133114
        },
        {
          "count": 6,
          "country": "CN",
          "recent": 0,
          "volume": 3403523.1807560055
        },
        {
          "count": 5,
          "country": "PK",
          "recent": 1,
          "volume": 11352501.790262004
        },
        {
          "count": 4,
          "country": "LK",
          "recent": 0,
          "volume": 6256591.438772
        },
        {
          "count": 2,
          "country": "MX",
          "recent": 0,
          "volume": 4453241.105427993
        },
        {
          "count": 2,
          "country": "PS",
          "recent": 0,
          "volume": 9445809.073918557
        },
        {
          "count": 2,
          "country": "JO",
          "recent": 0,
          "volume": 3128295.719386
        },
        {
          "count": 2,
          "country": "CY",
          "recent": 0,
          "volume": 2127760.9801980094
        },
        {
          "count": 2,
          "country": "TR",
          "recent": 0,
          "volume": 265206.80160399986
        },
        {
          "count": 1,
          "country": "ET",
          "recent": 0,
          "volume": 2195.1211489999996
        },
        {
          "count": 1,
          "country": "VE",
          "recent": 0,
          "volume": 3338164.9931884687
        },
        {
          "count": 1,
          "country": "MT",
          "recent": 0,
          "volume": 507619.4175730005
        },
        {
          "count": 1,
          "country": "JP",
          "recent": 0,
          "volume": 1956437.4004499982
        },
        {
          "count": 1,
          "country": "EC",
          "recent": 0,
          "volume": 662097.7627120002
        },
        {
          "count": 1,
          "country": "FI",
          "recent": 0,
          "volume": 763234.1115349992
        },
        {
          "count": 1,
          "country": "AF",
          "recent": 0,
          "volume": 1564147.859693
        },
        {
          "count": 1,
          "country": "GR",
          "recent": 1,
          "volume": 0
        },
        {
          "count": 1,
          "country": "BR",
          "recent": 0,
          "volume": 6069217.362338002
        },
        {
          "count": 1,
          "country": "ZA",
          "recent": 0,
          "volume": 1564147.859693
        },
        {
          "count": 1,
          "country": "LT",
          "recent": 0,
          "volume": 1207348.5759129988
        }
      ],
      "diamonds": [
        {
          "a": 10170.907,
          "s": "BUY",
          "t": "March 31"
        },
        {
          "a": 19867.88699,
          "s": "SELL",
          "t": "25+ bps increase"
        },
        {
          "a": 11073.70322,
          "s": "BUY",
          "t": "March 7"
        },
        {
          "a": 21978,
          "s": "BUY",
          "t": "74,000"
        },
        {
          "a": 10374.1796,
          "s": "BUY",
          "t": "Up"
        },
        {
          "a": 14100,
          "s": "SELL",
          "t": "\u2191 $200"
        },
        {
          "a": 10800,
          "s": "BUY",
          "t": "April 30"
        },
        {
          "a": 18612.517,
          "s": "BUY",
          "t": "Up"
        },
        {
          "a": 27523.059,
          "s": "BUY",
          "t": "Up"
        },
        {
          "a": 14444.1851,
          "s": "SELL",
          "t": "\u2191 80,000"
        },
        {
          "a": 19185.4392,
          "s": "BUY",
          "t": "Up"
        },
        {
          "a": 14160.622,
          "s": "BUY",
          "t": "March 7"
        },
        {
          "a": 27991.05679,
          "s": "BUY",
          "t": "March 8"
        },
        {
          "a": 10267.7902,
          "s": "BUY",
          "t": "Up"
        },
        {
          "a": 33884.80128,
          "s": "SELL",
          "t": "Delaware"
        },
        {
          "a": 10981.38322,
          "s": "BUY",
          "t": "March 6"
        },
        {
          "a": 14110.72515,
          "s": "BUY",
          "t": "76,000"
        },
        {
          "a": 19980,
          "s": "BUY",
          "t": "76,000"
        },
        {
          "a": 10338.509999,
          "s": "BUY",
          "t": ""
        },
        {
          "a": 14226.72753,
          "s": "BUY",
          "t": "\u2193 65,000"
        },
        {
          "a": 42396.749912,
          "s": "BUY",
          "t": "March 7"
        },
        {
          "a": 12551.236,
          "s": "BUY",
          "t": ">2,400"
        },
        {
          "a": 15425.4,
          "s": "BUY",
          "t": ""
        },
        {
          "a": 10091.1908,
          "s": "BUY",
          "t": "Delaware"
        },
        {
          "a": 14599.999998,
          "s": "BUY",
          "t": ""
        },
        {
          "a": 10695.59987,
          "s": "BUY",
          "t": "Position abolished"
        },
        {
          "a": 11999.999998,
          "s": "BUY",
          "t": "March 15"
        },
        {
          "a": 14999.99988,
          "s": "BUY",
          "t": "March 8"
        },
        {
          "a": 13987.4711,
          "s": "BUY",
          "t": "Up"
        },
        {
          "a": 14580.84456,
          "s": "BUY",
          "t": "45\u201350M"
        }
      ],
      "dots": [
        {
          "c": "GB",
          "l": "high"
        },
        {
          "c": "US",
          "l": "high"
        },
        {
          "c": "US",
          "l": "critical"
        },
        {
          "c": "IR",
          "l": "critical"
        },
        {
          "c": "US",
          "l": "critical"
        },
        {
          "c": "IR",
          "l": "critical"
        },
        {
          "c": "US",
          "l": "critical"
        },
        {
          "c": "IL",
          "l": "critical"
        },
        {
          "c": "IR",
          "l": "critical"
        },
        {
          "c": "US",
          "l": "critical"
        },
        {
          "c": "CN",
          "l": "critical"
        },
        {
          "c": "IR",
          "l": "critical"
        },
        {
          "c": "IR",
          "l": "critical"
        },
        {
          "c": "IR",
          "l": "critical"
        },
        {
          "c": "IL",
          "l": "critical"
        },
        {
          "c": "LB",
          "l": "critical"
        },
        {
          "c": "RU",
          "l": "critical"
        },
        {
          "c": "US",
          "l": "critical"
        },
        {
          "c": "US",
          "l": "critical"
        },
        {
          "c": "UA",
          "l": "critical"
        },
        {
          "c": "IR",
          "l": "critical"
        },
        {
          "c": "IR",
          "l": "critical"
        },
        {
          "c": "LB",
          "l": "critical"
        },
        {
          "c": "IR",
          "l": "critical"
        },
        {
          "c": "IR",
          "l": "critical"
        },
        {
          "c": "IR",
          "l": "critical"
        },
        {
          "c": "US",
          "l": "critical"
        },
        {
          "c": "US",
          "l": "critical"
        },
        {
          "c": "IL",
          "l": "critical"
        },
        {
          "c": "IL",
          "l": "critical"
        },
        {
          "c": "IL",
          "l": "critical"
        },
        {
          "c": "US",
          "l": "critical"
        },
        {
          "c": "US",
          "l": "critical"
        },
        {
          "c": "IL",
          "l": "critical"
        },
        {
          "c": "US",
          "l": "critical"
        },
        {
          "c": "IL",
          "l": "critical"
        },
        {
          "c": "IL",
          "l": "critical"
        },
        {
          "c": "IR",
          "l": "critical"
        },
        {
          "c": "AE",
          "l": "critical"
        },
        {
          "c": "LB",
          "l": "critical"
        },
        {
          "c": "IQ",
          "l": "critical"
        },
        {
          "c": "IR",
          "l": "critical"
        },
        {
          "c": "US",
          "l": "critical"
        },
        {
          "c": "KW",
          "l": "critical"
        },
        {
          "c": "US",
          "l": "critical"
        },
        {
          "c": "IR",
          "l": "critical"
        },
        {
          "c": "IL",
          "l": "critical"
        },
        {
          "c": "IL",
          "l": "critical"
        },
        {
          "c": "IL",
          "l": "critical"
        },
        {
          "c": "IR",
          "l": "critical"
        }
      ],
      "flights": [
        {
          "cat": "Doomsday",
          "cs": "N/A",
          "lat": 38.7233,
          "lng": -76.8728,
          "ts": 1772925559394
        },
        {
          "cat": "Drone",
          "cs": "RFR7331",
          "lat": 34.5649,
          "lng": 34.9933,
          "ts": 1772923542323
        },
        {
          "cat": "Presidential",
          "cs": "N/A",
          "lat": 28.5966,
          "lng": -79.0009,
          "ts": 1772921807030
        },
        {
          "cat": "Presidential",
          "cs": "SAM422",
          "lat": 33.3509,
          "lng": -81.9619,
          "ts": 1772921746196
        },
        {
          "cat": "Presidential",
          "cs": "SAM441",
          "lat": 33.7898,
          "lng": -77.5715,
          "ts": 1772921441042
        },
        {
          "cat": "Heavy Cargo",
          "cs": "SUM9105",
          "lat": 33.6722,
          "lng": 35.2847,
          "ts": 1772921317848
        },
        {
          "cat": "Tanker",
          "cs": "CFC3212",
          "lat": 60.6167,
          "lng": -135.0801,
          "ts": 1772920587609
        },
        {
          "cat": "Presidential",
          "cs": "AF2",
          "lat": 39.3106,
          "lng": -75.5657,
          "ts": 1772918201756
        },
        {
          "cat": "Doomsday",
          "cs": "N/A",
          "lat": 38.2042,
          "lng": -105.2874,
          "ts": 1772912254881
        },
        {
          "cat": "Drone",
          "cs": "AS2132",
          "lat": 34.9341,
          "lng": 15.3443,
          "ts": 1772909478115
        },
        {
          "cat": "Drone",
          "cs": "AS2132",
          "lat": 34.9341,
          "lng": 15.3443,
          "ts": 1772909476150
        },
        {
          "cat": "Presidential",
          "cs": "NAF15",
          "lat": 53.0116,
          "lng": -13.4834,
          "ts": 1772908987052
        }
      ],
      "_scraped_at": "2026-03-07T23:42:54.285905+00:00",
      "_source": "api",
      "_source_api_url": "https://api-v2.glint.trade/api/public/globe"
    }
  ]
}