{
  "scraped_at": "2026-04-23T08:02:17.501983+00:00",
  "source_url": "https://glint.trade/feed",
  "item_count": 2,
  "items": [
    {
      "error": "missing authorization header",
      "_scraped_at": "2026-04-23T08:02:17.501983+00:00",
      "_source": "api",
      "_source_api_url": "https://api-v2.glint.trade/api/geolocations/events"
    },
    {
      "countries": [
        {
          "count": 44,
          "country": "IR",
          "recent": 3,
          "volume": 505768919.14601254
        },
        {
          "count": 43,
          "country": "US",
          "recent": 2,
          "volume": 433024762.03484756
        },
        {
          "count": 8,
          "country": "LB",
          "recent": 0,
          "volume": 2064371.5066229992
        },
        {
          "count": 8,
          "country": "PK",
          "recent": 0,
          "volume": 55466725.43627124
        },
        {
          "count": 7,
          "country": "UA",
          "recent": 1,
          "volume": 62185545.6524548
        },
        {
          "count": 7,
          "country": "FR",
          "recent": 2,
          "volume": 112792703.75546142
        },
        {
          "count": 5,
          "country": "IL",
          "recent": 0,
          "volume": 27955934.343625
        },
        {
          "count": 4,
          "country": "GB",
          "recent": 1,
          "volume": 52462087.04067172
        },
        {
          "count": 4,
          "country": "RU",
          "recent": 0,
          "volume": 31116864.43595488
        },
        {
          "count": 2,
          "country": "CH",
          "recent": 1,
          "volume": 27167747.18236386
        },
        {
          "count": 1,
          "country": "OM",
          "recent": 0,
          "volume": 1293920.8751550002
        },
        {
          "count": 1,
          "country": "IT",
          "recent": 1,
          "volume": 0
        },
        {
          "count": 1,
          "country": "GE",
          "recent": 0,
          "volume": 130138.57277199998
        },
        {
          "count": 1,
          "country": "HU",
          "recent": 0,
          "volume": 46978594.49165181
        },
        {
          "count": 1,
          "country": "IQ",
          "recent": 0,
          "volume": 643008.5175210002
        },
        {
          "count": 1,
          "country": "ZA",
          "recent": 1,
          "volume": 0
        },
        {
          "count": 1,
          "country": "SK",
          "recent": 1,
          "volume": 0
        },
        {
          "count": 1,
          "country": "VN",
          "recent": 1,
          "volume": 0
        },
        {
          "count": 1,
          "country": "EC",
          "recent": 0,
          "volume": 1925180.193977004
        },
        {
          "count": 1,
          "country": "BG",
          "recent": 0,
          "volume": 182182.521779
        },
        {
          "count": 1,
          "country": "KR",
          "recent": 1,
          "volume": 0
        },
        {
          "count": 1,
          "country": "HK",
          "recent": 1,
          "volume": 0
        }
      ],
      "diamonds": [
        {
          "a": 50697.4,
          "s": "BUY",
          "t": "April 30"
        },
        {
          "a": 20026.6365,
          "s": "BUY",
          "t": "\u2193 $70"
        },
        {
          "a": 22577.4,
          "s": "BUY",
          "t": "50+ bps decrease"
        },
        {
          "a": 22677.3,
          "s": "BUY",
          "t": "50+ bps decrease"
        },
        {
          "a": 22777.2,
          "s": "BUY",
          "t": "50+ bps decrease"
        },
        {
          "a": 22827.15,
          "s": "BUY",
          "t": "50+ bps decrease"
        },
        {
          "a": 22977,
          "s": "BUY",
          "t": "50+ bps decrease"
        },
        {
          "a": 22777.2,
          "s": "BUY",
          "t": "50+ bps decrease"
        },
        {
          "a": 22877.1,
          "s": "BUY",
          "t": "50+ bps decrease"
        },
        {
          "a": 22677.3,
          "s": "BUY",
          "t": "50+ bps decrease"
        },
        {
          "a": 22877.1,
          "s": "BUY",
          "t": "50+ bps decrease"
        },
        {
          "a": 22977,
          "s": "BUY",
          "t": "50+ bps decrease"
        },
        {
          "a": 22977,
          "s": "BUY",
          "t": "50+ bps decrease"
        },
        {
          "a": 22377.6,
          "s": "BUY",
          "t": "50+ bps decrease"
        },
        {
          "a": 21878.1,
          "s": "BUY",
          "t": "50+ bps decrease"
        },
        {
          "a": 22477.5,
          "s": "BUY",
          "t": "50+ bps decrease"
        },
        {
          "a": 20779.2,
          "s": "BUY",
          "t": "50+ bps decrease"
        },
        {
          "a": 23076.9,
          "s": "BUY",
          "t": "50+ bps decrease"
        },
        {
          "a": 22477.5,
          "s": "BUY",
          "t": "50+ bps decrease"
        },
        {
          "a": 22677.3,
          "s": "BUY",
          "t": "50+ bps decrease"
        },
        {
          "a": 22977,
          "s": "BUY",
          "t": "50+ bps decrease"
        },
        {
          "a": 21978,
          "s": "BUY",
          "t": "50+ bps decrease"
        },
        {
          "a": 21878.1,
          "s": "BUY",
          "t": "50+ bps decrease"
        },
        {
          "a": 21778.2,
          "s": "BUY",
          "t": "50+ bps decrease"
        },
        {
          "a": 21678.3,
          "s": "BUY",
          "t": "50+ bps decrease"
        },
        {
          "a": 21578.4,
          "s": "BUY",
          "t": "50+ bps decrease"
        },
        {
          "a": 21878.1,
          "s": "BUY",
          "t": "50+ bps decrease"
        },
        {
          "a": 21778.2,
          "s": "BUY",
          "t": "50+ bps decrease"
        },
        {
          "a": 21678.3,
          "s": "BUY",
          "t": "50+ bps decrease"
        },
        {
          "a": 21778.2,
          "s": "BUY",
          "t": "50+ bps decrease"
        }
      ],
      "dots": [
        {
          "c": "IR",
          "l": "high"
        },
        {
          "c": "IL",
          "l": "high"
        },
        {
          "c": "US",
          "l": "high"
        },
        {
          "c": "OM",
          "l": "high"
        },
        {
          "c": "US",
          "l": "high"
        },
        {
          "c": "RU",
          "l": "high"
        },
        {
          "c": "US",
          "l": "high"
        },
        {
          "c": "US",
          "l": "high"
        },
        {
          "c": "IR",
          "l": "high"
        },
        {
          "c": "IR",
          "l": "high"
        },
        {
          "c": "LB",
          "l": "high"
        },
        {
          "c": "FR",
          "l": "high"
        },
        {
          "c": "IR",
          "l": "high"
        },
        {
          "c": "IR",
          "l": "high"
        },
        {
          "c": "FR",
          "l": "high"
        },
        {
          "c": "IR",
          "l": "high"
        },
        {
          "c": "US",
          "l": "high"
        },
        {
          "c": "IR",
          "l": "high"
        },
        {
          "c": "US",
          "l": "high"
        },
        {
          "c": "IR",
          "l": "high"
        },
        {
          "c": "IL",
          "l": "high"
        },
        {
          "c": "IR",
          "l": "high"
        },
        {
          "c": "IR",
          "l": "high"
        },
        {
          "c": "US",
          "l": "high"
        },
        {
          "c": "GB",
          "l": "high"
        },
        {
          "c": "BG",
          "l": "high"
        },
        {
          "c": "IR",
          "l": "high"
        },
        {
          "c": "LB",
          "l": "high"
        },
        {
          "c": "IR",
          "l": "high"
        },
        {
          "c": "PK",
          "l": "high"
        },
        {
          "c": "US",
          "l": "high"
        },
        {
          "c": "US",
          "l": "high"
        },
        {
          "c": "IR",
          "l": "high"
        },
        {
          "c": "IR",
          "l": "high"
        },
        {
          "c": "US",
          "l": "high"
        },
        {
          "c": "IR",
          "l": "high"
        },
        {
          "c": "IR",
          "l": "high"
        },
        {
          "c": "US",
          "l": "high"
        },
        {
          "c": "IR",
          "l": "high"
        },
        {
          "c": "IR",
          "l": "high"
        },
        {
          "c": "RU",
          "l": "high"
        },
        {
          "c": "GE",
          "l": "high"
        },
        {
          "c": "IR",
          "l": "high"
        },
        {
          "c": "US",
          "l": "high"
        },
        {
          "c": "IL",
          "l": "high"
        },
        {
          "c": "US",
          "l": "high"
        },
        {
          "c": "US",
          "l": "high"
        },
        {
          "c": "PK",
          "l": "high"
        },
        {
          "c": "IR",
          "l": "high"
        },
        {
          "c": "IR",
          "l": "high"
        }
      ],
      "flights": [
        {
          "cat": "Presidential",
          "cs": "RRR1231",
          "lat": 51.5849,
          "lng": -0.3732,
          "ts": 1776929109919
        },
        {
          "cat": "Presidential",
          "cs": "RSD956",
          "lat": 55.5848,
          "lng": 37.1512,
          "ts": 1776924556061
        },
        {
          "cat": "Presidential",
          "cs": "UKN1117",
          "lat": 50.069,
          "lng": 19.7232,
          "ts": 1776922836459
        },
        {
          "cat": "Royal",
          "cs": "INDIA2",
          "lat": 28.517,
          "lng": 76.8255,
          "ts": 1776916686481
        },
        {
          "cat": "AWACS",
          "cs": "MTCH12",
          "lat": -27.8358,
          "lng": 149.4103,
          "ts": 1776916564322
        }
      ],
      "_scraped_at": "2026-04-23T08:02:17.501983+00:00",
      "_source": "api",
      "_source_api_url": "https://api-v2.glint.trade/api/public/globe"
    }
  ]
}