{
  "scraped_at": "2026-05-09T22:34:33.547353+00:00",
  "source_url": "https://glint.trade/feed",
  "item_count": 2,
  "items": [
    {
      "error": "missing authorization header",
      "_scraped_at": "2026-05-09T22:34:33.547353+00:00",
      "_source": "api",
      "_source_api_url": "https://api-v2.glint.trade/api/geolocations/events"
    },
    {
      "countries": [
        {
          "count": 35,
          "country": "US",
          "recent": 12,
          "volume": 107467778.83833474
        },
        {
          "count": 18,
          "country": "UA",
          "recent": 2,
          "volume": 1508188129.2934196
        },
        {
          "count": 16,
          "country": "IR",
          "recent": 3,
          "volume": 154776355.76513764
        },
        {
          "count": 11,
          "country": "RU",
          "recent": 0,
          "volume": 653491308.3925322
        },
        {
          "count": 9,
          "country": "GB",
          "recent": 4,
          "volume": 3888446.9311812604
        },
        {
          "count": 5,
          "country": "IL",
          "recent": 0,
          "volume": 110513543.2275245
        },
        {
          "count": 4,
          "country": "HU",
          "recent": 0,
          "volume": 24623597.501291864
        },
        {
          "count": 4,
          "country": "QA",
          "recent": 0,
          "volume": 76585920.80601308
        },
        {
          "count": 3,
          "country": "LB",
          "recent": 0,
          "volume": 1821842.4866551599
        },
        {
          "count": 3,
          "country": "DE",
          "recent": 1,
          "volume": 2972513.5211386317
        },
        {
          "count": 2,
          "country": "IN",
          "recent": 0,
          "volume": 407087.5289294002
        },
        {
          "count": 2,
          "country": "PK",
          "recent": 0,
          "volume": 876577.406802999
        },
        {
          "count": 2,
          "country": "BR",
          "recent": 2,
          "volume": 0
        },
        {
          "count": 1,
          "country": "JP",
          "recent": 0,
          "volume": 0
        },
        {
          "count": 1,
          "country": "MX",
          "recent": 0,
          "volume": 0
        },
        {
          "count": 1,
          "country": "CN",
          "recent": 0,
          "volume": 5670966.546001032
        },
        {
          "count": 1,
          "country": "ZA",
          "recent": 0,
          "volume": 0
        },
        {
          "count": 1,
          "country": "KE",
          "recent": 0,
          "volume": 0
        }
      ],
      "diamonds": [
        {
          "a": 19300,
          "s": "BUY",
          "t": ""
        },
        {
          "a": 19580,
          "s": "BUY",
          "t": ""
        },
        {
          "a": 10765.75438,
          "s": "BUY",
          "t": ""
        },
        {
          "a": 23649.33746,
          "s": "BUY",
          "t": "May 14"
        },
        {
          "a": 47758.20642,
          "s": "BUY",
          "t": "May 11"
        },
        {
          "a": 10001.3921,
          "s": "BUY",
          "t": ""
        },
        {
          "a": 10047.51106,
          "s": "SELL",
          "t": ""
        },
        {
          "a": 18500,
          "s": "BUY",
          "t": "May 31"
        },
        {
          "a": 13757.6212,
          "s": "BUY",
          "t": "May 31"
        },
        {
          "a": 16289.77176,
          "s": "BUY",
          "t": "May 15"
        },
        {
          "a": 14868.67294,
          "s": "BUY",
          "t": ""
        },
        {
          "a": 151548.3,
          "s": "BUY",
          "t": "\u2193 73,000"
        },
        {
          "a": 27946.49538,
          "s": "BUY",
          "t": "May 15"
        },
        {
          "a": 14386.5656,
          "s": "BUY",
          "t": ""
        },
        {
          "a": 10784.86824,
          "s": "SELL",
          "t": "No change"
        },
        {
          "a": 10019.72,
          "s": "BUY",
          "t": "May 13"
        },
        {
          "a": 34659.4952,
          "s": "BUY",
          "t": ""
        },
        {
          "a": 69833.84535,
          "s": "BUY",
          "t": "May 15"
        },
        {
          "a": 64985.00775,
          "s": "SELL",
          "t": "May 8"
        },
        {
          "a": 14901.7475,
          "s": "BUY",
          "t": "May 31"
        },
        {
          "a": 10190.13,
          "s": "BUY",
          "t": "May 31"
        },
        {
          "a": 25230,
          "s": "BUY",
          "t": "\u2191 $150"
        },
        {
          "a": 23741.9049,
          "s": "SELL",
          "t": "\u2191 $175"
        },
        {
          "a": 25554.9308,
          "s": "SELL",
          "t": ""
        },
        {
          "a": 14118.22267,
          "s": "SELL",
          "t": "June 30"
        },
        {
          "a": 12902.824,
          "s": "BUY",
          "t": ""
        },
        {
          "a": 14364.5856,
          "s": "SELL",
          "t": "May 13"
        },
        {
          "a": 25453.41631,
          "s": "SELL",
          "t": "May 11"
        },
        {
          "a": 17600,
          "s": "BUY",
          "t": ""
        },
        {
          "a": 19800.57885,
          "s": "BUY",
          "t": "Spain"
        }
      ],
      "dots": [
        {
          "c": "IR",
          "l": "high"
        },
        {
          "c": "DE",
          "l": "high"
        },
        {
          "c": "GB",
          "l": "high"
        },
        {
          "c": "UA",
          "l": "high"
        },
        {
          "c": "IR",
          "l": "high"
        },
        {
          "c": "IR",
          "l": "high"
        },
        {
          "c": "IN",
          "l": "high"
        },
        {
          "c": "UA",
          "l": "high"
        },
        {
          "c": "RU",
          "l": "high"
        },
        {
          "c": "QA",
          "l": "high"
        },
        {
          "c": "UA",
          "l": "high"
        },
        {
          "c": "UA",
          "l": "high"
        },
        {
          "c": "CN",
          "l": "high"
        },
        {
          "c": "UA",
          "l": "high"
        },
        {
          "c": "UA",
          "l": "high"
        },
        {
          "c": "RU",
          "l": "high"
        },
        {
          "c": "UA",
          "l": "high"
        },
        {
          "c": "US",
          "l": "high"
        },
        {
          "c": "PK",
          "l": "high"
        },
        {
          "c": "US",
          "l": "high"
        },
        {
          "c": "QA",
          "l": "high"
        },
        {
          "c": "RU",
          "l": "high"
        },
        {
          "c": "RU",
          "l": "high"
        },
        {
          "c": "RU",
          "l": "high"
        },
        {
          "c": "RU",
          "l": "high"
        },
        {
          "c": "US",
          "l": "high"
        },
        {
          "c": "UA",
          "l": "high"
        },
        {
          "c": "LB",
          "l": "high"
        },
        {
          "c": "RU",
          "l": "high"
        },
        {
          "c": "US",
          "l": "high"
        },
        {
          "c": "US",
          "l": "high"
        },
        {
          "c": "US",
          "l": "high"
        },
        {
          "c": "RU",
          "l": "high"
        },
        {
          "c": "US",
          "l": "high"
        },
        {
          "c": "GB",
          "l": "high"
        },
        {
          "c": "US",
          "l": "high"
        },
        {
          "c": "IR",
          "l": "high"
        },
        {
          "c": "HU",
          "l": "high"
        },
        {
          "c": "RU",
          "l": "high"
        },
        {
          "c": "HU",
          "l": "high"
        },
        {
          "c": "IR",
          "l": "high"
        },
        {
          "c": "IR",
          "l": "high"
        },
        {
          "c": "LB",
          "l": "high"
        },
        {
          "c": "UA",
          "l": "critical"
        },
        {
          "c": "UA",
          "l": "critical"
        },
        {
          "c": "US",
          "l": "critical"
        },
        {
          "c": "UA",
          "l": "critical"
        },
        {
          "c": "US",
          "l": "critical"
        },
        {
          "c": "UA",
          "l": "critical"
        },
        {
          "c": "UA",
          "l": "critical"
        }
      ],
      "flights": [
        {
          "cat": "Drone",
          "cs": "TROY703",
          "lat": 31.3034,
          "lng": -100.4468,
          "ts": 1778362094642
        },
        {
          "cat": "NASA/Science",
          "cs": "NASA806",
          "lat": 30.6855,
          "lng": -104.8144,
          "ts": 1778357996296
        },
        {
          "cat": "NASA/Science",
          "cs": "NASA802",
          "lat": -7.6503,
          "lng": -79.6251,
          "ts": 1778354113976
        },
        {
          "cat": "Presidential",
          "cs": "SAM459",
          "lat": 39.2831,
          "lng": -74.2843,
          "ts": 1778350527872
        }
      ],
      "_scraped_at": "2026-05-09T22:34:33.547353+00:00",
      "_source": "api",
      "_source_api_url": "https://api-v2.glint.trade/api/public/globe"
    }
  ]
}