{
  "scraped_at": "2026-03-04T21:56:16.848158+00:00",
  "source_url": "https://glint.trade/feed",
  "item_count": 1,
  "items": [
    {
      "countries": [
        {
          "count": 317,
          "country": "IR",
          "recent": 23,
          "volume": 739656549.1977355
        },
        {
          "count": 301,
          "country": "US",
          "recent": 34,
          "volume": 526096452.2877087
        },
        {
          "count": 180,
          "country": "IL",
          "recent": 10,
          "volume": 305750651.7412766
        },
        {
          "count": 65,
          "country": "LB",
          "recent": 0,
          "volume": 41021904.74239521
        },
        {
          "count": 30,
          "country": "LK",
          "recent": 0,
          "volume": 53138834.74298628
        },
        {
          "count": 20,
          "country": "IQ",
          "recent": 2,
          "volume": 20268431.675174024
        },
        {
          "count": 18,
          "country": "TR",
          "recent": 0,
          "volume": 46255918.03047727
        },
        {
          "count": 16,
          "country": "GB",
          "recent": 0,
          "volume": 134535868.6933069
        },
        {
          "count": 16,
          "country": "QA",
          "recent": 1,
          "volume": 25734314.807682544
        },
        {
          "count": 14,
          "country": "CN",
          "recent": 0,
          "volume": 143765424.65514404
        },
        {
          "count": 14,
          "country": "UA",
          "recent": 0,
          "volume": 353474785.9527945
        },
        {
          "count": 12,
          "country": "RU",
          "recent": 0,
          "volume": 184095238.643463
        },
        {
          "count": 11,
          "country": "SA",
          "recent": 0,
          "volume": 3626609.5733496826
        },
        {
          "count": 11,
          "country": "BH",
          "recent": 1,
          "volume": 15495569.933944242
        },
        {
          "count": 10,
          "country": "AE",
          "recent": 0,
          "volume": 12989411.803991228
        },
        {
          "count": 6,
          "country": "KW",
          "recent": 0,
          "volume": 8556763.040558502
        },
        {
          "count": 6,
          "country": "ES",
          "recent": 0,
          "volume": 1944715.068116187
        },
        {
          "count": 6,
          "country": "VE",
          "recent": 3,
          "volume": 8505740.373018043
        },
        {
          "count": 5,
          "country": "DE",
          "recent": 0,
          "volume": 3797553.9808711223
        },
        {
          "count": 4,
          "country": "AF",
          "recent": 0,
          "volume": 4631875.878318668
        },
        {
          "count": 4,
          "country": "PS",
          "recent": 0,
          "volume": 3626948.486532395
        },
        {
          "count": 4,
          "country": "YE",
          "recent": 0,
          "volume": 394753.92310576007
        },
        {
          "count": 4,
          "country": "KR",
          "recent": 0,
          "volume": 5592684.47951561
        },
        {
          "count": 3,
          "country": "OM",
          "recent": 0,
          "volume": 3874181.532282534
        },
        {
          "count": 3,
          "country": "AZ",
          "recent": 0,
          "volume": 3030762.3596840734
        },
        {
          "count": 3,
          "country": "IN",
          "recent": 0,
          "volume": 2585175.3616302465
        },
        {
          "count": 3,
          "country": "MT",
          "recent": 0,
          "volume": 1920794.6723714604
        },
        {
          "count": 2,
          "country": "HU",
          "recent": 0,
          "volume": 1878842.329714037
        },
        {
          "count": 2,
          "country": "EC",
          "recent": 0,
          "volume": 164989.42767695003
        },
        {
          "count": 2,
          "country": "JO",
          "recent": 0,
          "volume": 25860.305261
        },
        {
          "count": 2,
          "country": "ET",
          "recent": 0,
          "volume": 27199.897914
        },
        {
          "count": 2,
          "country": "FR",
          "recent": 0,
          "volume": 3805907.8359395484
        },
        {
          "count": 2,
          "country": "SY",
          "recent": 0,
          "volume": 506937.89928769995
        },
        {
          "count": 2,
          "country": "SD",
          "recent": 0,
          "volume": 2926973.351654073
        },
        {
          "count": 2,
          "country": "PK",
          "recent": 0,
          "volume": 3083391.943031081
        },
        {
          "count": 1,
          "country": "GL",
          "recent": 0,
          "volume": 1004053.9513300001
        },
        {
          "count": 1,
          "country": "JP",
          "recent": 0,
          "volume": 93728.15168976999
        },
        {
          "count": 1,
          "country": "CU",
          "recent": 0,
          "volume": 1557396.771568
        },
        {
          "count": 1,
          "country": "CY",
          "recent": 0,
          "volume": 1612411.7848148898
        },
        {
          "count": 1,
          "country": "PH",
          "recent": 0,
          "volume": 4037.228993
        },
        {
          "count": 1,
          "country": "SG",
          "recent": 0,
          "volume": 1463486.675827037
        },
        {
          "count": 1,
          "country": "AU",
          "recent": 1,
          "volume": 0
        },
        {
          "count": 1,
          "country": "CA",
          "recent": 0,
          "volume": 1724576.11003589
        },
        {
          "count": 1,
          "country": "NL",
          "recent": 0,
          "volume": 90738.70019699998
        },
        {
          "count": 1,
          "country": "SK",
          "recent": 0,
          "volume": 37121518.10126099
        }
      ],
      "diamonds": [
        {
          "a": 17695.325563,
          "s": "SELL",
          "t": "Up"
        },
        {
          "a": 71737.28016,
          "s": "BUY",
          "t": "No change"
        },
        {
          "a": 11416.8374,
          "s": "BUY",
          "t": "March 4"
        },
        {
          "a": 10707.3864,
          "s": "BUY",
          "t": "Oklahoma City Thunder"
        },
        {
          "a": 14896.9464,
          "s": "SELL",
          "t": "Waste"
        },
        {
          "a": 11999.999997,
          "s": "BUY",
          "t": "June 30"
        },
        {
          "a": 13999.999998,
          "s": "BUY",
          "t": "June 30"
        },
        {
          "a": 11970.68733,
          "s": "BUY",
          "t": "Win Senate Race"
        },
        {
          "a": 10000,
          "s": "BUY",
          "t": "Man City"
        },
        {
          "a": 18290.168072,
          "s": "SELL",
          "t": "Up"
        },
        {
          "a": 12714.6894,
          "s": "BUY",
          "t": "Up"
        },
        {
          "a": 12611.896,
          "s": "BUY",
          "t": "Arsenal"
        },
        {
          "a": 11995.50915,
          "s": "BUY",
          "t": "\u2191 80,000"
        },
        {
          "a": 22523.8278,
          "s": "BUY",
          "t": "Up"
        },
        {
          "a": 49999.999998,
          "s": "BUY",
          "t": "March 6"
        },
        {
          "a": 22463.34203,
          "s": "BUY",
          "t": "March 3"
        },
        {
          "a": 49999.999987,
          "s": "BUY",
          "t": "March 6"
        },
        {
          "a": 20169.74374,
          "s": "BUY",
          "t": "\u2191 100,000"
        },
        {
          "a": 28243.60245,
          "s": "BUY",
          "t": "March 31"
        },
        {
          "a": 17132.76009,
          "s": "BUY",
          "t": "March 15"
        },
        {
          "a": 13939.37667,
          "s": "BUY",
          "t": "Up"
        },
        {
          "a": 11735.471189,
          "s": "SELL",
          "t": "Up"
        },
        {
          "a": 30741.3279,
          "s": "BUY",
          "t": "State of the Union"
        },
        {
          "a": 14404.72086,
          "s": "SELL",
          "t": "Up"
        },
        {
          "a": 20704.76451,
          "s": "BUY",
          "t": "58,000-60,000"
        },
        {
          "a": 12229.18857,
          "s": "BUY",
          "t": "<58,000"
        },
        {
          "a": 22108.8,
          "s": "SELL",
          "t": "Tucker Carlson"
        },
        {
          "a": 199196.0096,
          "s": "BUY",
          "t": "Waste"
        },
        {
          "a": 46329.62007,
          "s": "BUY",
          "t": "US"
        },
        {
          "a": 13352.46955,
          "s": "SELL",
          "t": "Wesley Hunt"
        }
      ],
      "dots": [
        {
          "c": "IR",
          "l": "high"
        },
        {
          "c": "IR",
          "l": "high"
        },
        {
          "c": "US",
          "l": "high"
        },
        {
          "c": "IR",
          "l": "high"
        },
        {
          "c": "US",
          "l": "critical"
        },
        {
          "c": "US",
          "l": "critical"
        },
        {
          "c": "KR",
          "l": "critical"
        },
        {
          "c": "IR",
          "l": "critical"
        },
        {
          "c": "IR",
          "l": "critical"
        },
        {
          "c": "US",
          "l": "critical"
        },
        {
          "c": "KW",
          "l": "critical"
        },
        {
          "c": "BH",
          "l": "critical"
        },
        {
          "c": "IN",
          "l": "critical"
        },
        {
          "c": "IR",
          "l": "critical"
        },
        {
          "c": "IL",
          "l": "critical"
        },
        {
          "c": "US",
          "l": "critical"
        },
        {
          "c": "IN",
          "l": "critical"
        },
        {
          "c": "IL",
          "l": "critical"
        },
        {
          "c": "IR",
          "l": "critical"
        },
        {
          "c": "IR",
          "l": "critical"
        },
        {
          "c": "IL",
          "l": "critical"
        },
        {
          "c": "US",
          "l": "critical"
        },
        {
          "c": "US",
          "l": "critical"
        },
        {
          "c": "US",
          "l": "critical"
        },
        {
          "c": "US",
          "l": "critical"
        },
        {
          "c": "GB",
          "l": "critical"
        },
        {
          "c": "IR",
          "l": "critical"
        },
        {
          "c": "US",
          "l": "critical"
        },
        {
          "c": "IL",
          "l": "critical"
        },
        {
          "c": "US",
          "l": "critical"
        },
        {
          "c": "IR",
          "l": "critical"
        },
        {
          "c": "IR",
          "l": "critical"
        },
        {
          "c": "IL",
          "l": "critical"
        }
      ],
      "flights": [
        {
          "cat": "Doomsday",
          "cs": "N/A",
          "lat": 37.6019,
          "lng": -77.3349,
          "ts": 1772660370114
        },
        {
          "cat": "Other",
          "cs": "UAE98P",
          "lat": 23.8068,
          "lng": 55.4685,
          "ts": 1772660051130
        },
        {
          "cat": "Other",
          "cs": "UAE2",
          "lat": 22.8284,
          "lng": 54.248,
          "ts": 1772659149239
        },
        {
          "cat": "Other",
          "cs": "RJA622",
          "lat": 31.6889,
          "lng": 35.8527,
          "ts": 1772657940877
        },
        {
          "cat": "Other",
          "cs": "UAE355",
          "lat": 24.7297,
          "lng": 56.3205,
          "ts": 1772656737463
        },
        {
          "cat": "Doomsday",
          "cs": "N/A",
          "lat": 29.5534,
          "lng": -96.2063,
          "ts": 1772656698708
        },
        {
          "cat": "Drone",
          "cs": "VVPE804",
          "lat": 36.5081,
          "lng": 16.7345,
          "ts": 1772656453364
        },
        {
          "cat": "Other",
          "cs": "UAE65W",
          "lat": 22.8055,
          "lng": 54.1392,
          "ts": 1772656436623
        },
        {
          "cat": "Other",
          "cs": "UAE804",
          "lat": 23.0619,
          "lng": 55.1401,
          "ts": 1772655834494
        },
        {
          "cat": "Other",
          "cs": "ELY802",
          "lat": 32.2123,
          "lng": 34.9598,
          "ts": 1772653126314
        },
        {
          "cat": "Other",
          "cs": "ABY454",
          "lat": 25.3297,
          "lng": 55.5074,
          "ts": 1772651923648
        },
        {
          "cat": "Other",
          "cs": "WABEL08",
          "lat": 36.4571,
          "lng": -87.4984,
          "ts": 1772651322080
        },
        {
          "cat": "AWACS",
          "cs": "N/A",
          "lat": 61.3001,
          "lng": -149.7605,
          "ts": 1772650973899
        },
        {
          "cat": "Other",
          "cs": "YETI24",
          "lat": 32.0914,
          "lng": 34.5193,
          "ts": 1772650720976
        },
        {
          "cat": "Fighter",
          "cs": "N/A",
          "lat": 35.541,
          "lng": -97.3791,
          "ts": 1772648691452
        },
        {
          "cat": "Doomsday",
          "cs": "N/A",
          "lat": 41.1553,
          "lng": -95.9871,
          "ts": 1772648259497
        },
        {
          "cat": "Doomsday",
          "cs": "N/A",
          "lat": 41.126,
          "lng": -96.0885,
          "ts": 1772647892502
        },
        {
          "cat": "AWACS",
          "cs": "ASY050",
          "lat": 36.2279,
          "lng": -115.041,
          "ts": 1772647891674
        },
        {
          "cat": "Drone",
          "cs": "RFR7331",
          "lat": 34.5914,
          "lng": 32.9838,
          "ts": 1772647768888
        },
        {
          "cat": "Other",
          "cs": "UAE6FJ",
          "lat": 23.4772,
          "lng": 55.3736,
          "ts": 1772647715573
        },
        {
          "cat": "Other",
          "cs": "ABY422",
          "lat": 25.3296,
          "lng": 55.5074,
          "ts": 1772647414387
        },
        {
          "cat": "Presidential",
          "cs": "CTM1039",
          "lat": 49.0483,
          "lng": 1.2453,
          "ts": 1772647398764
        },
        {
          "cat": "Other",
          "cs": "UAE7CN",
          "lat": 23.5222,
          "lng": 55.3831,
          "ts": 1772645910826
        },
        {
          "cat": "Tanker",
          "cs": "THY6607",
          "lat": 51.0241,
          "lng": 11.1095,
          "ts": 1772645659055
        },
        {
          "cat": "Royal",
          "cs": "DUB4",
          "lat": 22.8888,
          "lng": 52.0981,
          "ts": 1772645076953
        },
        {
          "cat": "Other",
          "cs": "IAM1416",
          "lat": 25.1016,
          "lng": 56.83,
          "ts": 1772645008877
        },
        {
          "cat": "Other",
          "cs": "SEJ9082",
          "lat": 25.0974,
          "lng": 56.8215,
          "ts": 1772644707655
        },
        {
          "cat": "Other",
          "cs": "ABY620",
          "lat": 25.3296,
          "lng": 55.5074,
          "ts": 1772644406748
        },
        {
          "cat": "Other",
          "cs": "LOY872",
          "lat": 32.772,
          "lng": 33.2848,
          "ts": 1772643805411
        }
      ],
      "_scraped_at": "2026-03-04T21:56:16.848158+00:00",
      "_source": "api",
      "_source_api_url": "https://api.glint.trade/api/public/globe"
    }
  ]
}