{
  "scraped_at": "2026-03-20T09:04:24.790431+00:00",
  "source_url": "https://glint.trade/feed",
  "item_count": 2,
  "items": [
    {
      "error": "missing authorization header",
      "_scraped_at": "2026-03-20T09:04:24.790431+00:00",
      "_source": "api",
      "_source_api_url": "https://api-v2.glint.trade/api/geolocations/events"
    },
    {
      "countries": [
        {
          "count": 190,
          "country": "IR",
          "recent": 13,
          "volume": 759750422.8897756
        },
        {
          "count": 136,
          "country": "US",
          "recent": 9,
          "volume": 1090727911.6532729
        },
        {
          "count": 121,
          "country": "IL",
          "recent": 11,
          "volume": 360730427.6013056
        },
        {
          "count": 38,
          "country": "LB",
          "recent": 1,
          "volume": 3924433.6839847104
        },
        {
          "count": 25,
          "country": "CN",
          "recent": 3,
          "volume": 53947455.704724565
        },
        {
          "count": 23,
          "country": "UA",
          "recent": 1,
          "volume": 333868606.9947698
        },
        {
          "count": 21,
          "country": "RU",
          "recent": 2,
          "volume": 12520197.165664902
        },
        {
          "count": 19,
          "country": "GB",
          "recent": 3,
          "volume": 21333124.353693657
        },
        {
          "count": 14,
          "country": "QA",
          "recent": 1,
          "volume": 10616653.485315496
        },
        {
          "count": 14,
          "country": "IN",
          "recent": 1,
          "volume": 21039581.47370324
        },
        {
          "count": 10,
          "country": "SA",
          "recent": 0,
          "volume": 16997778.22995924
        },
        {
          "count": 9,
          "country": "JP",
          "recent": 1,
          "volume": 21612894.75646332
        },
        {
          "count": 7,
          "country": "AU",
          "recent": 0,
          "volume": 0
        },
        {
          "count": 6,
          "country": "KW",
          "recent": 1,
          "volume": 6262432.690577473
        },
        {
          "count": 6,
          "country": "DE",
          "recent": 1,
          "volume": 26994418.822244592
        },
        {
          "count": 5,
          "country": "PS",
          "recent": 1,
          "volume": 4018818.504245962
        },
        {
          "count": 4,
          "country": "KR",
          "recent": 1,
          "volume": 4221281.114754163
        },
        {
          "count": 4,
          "country": "AE",
          "recent": 0,
          "volume": 31486.381585859985
        },
        {
          "count": 4,
          "country": "BE",
          "recent": 1,
          "volume": 7343767.247407968
        },
        {
          "count": 3,
          "country": "CA",
          "recent": 0,
          "volume": 555891.5204119999
        },
        {
          "count": 3,
          "country": "MX",
          "recent": 1,
          "volume": 0
        },
        {
          "count": 3,
          "country": "OM",
          "recent": 0,
          "volume": 0
        },
        {
          "count": 3,
          "country": "TR",
          "recent": 0,
          "volume": 6319851.629707566
        },
        {
          "count": 3,
          "country": "NL",
          "recent": 0,
          "volume": 16175850.304836014
        },
        {
          "count": 3,
          "country": "SG",
          "recent": 0,
          "volume": 16164422.107059086
        },
        {
          "count": 3,
          "country": "GL",
          "recent": 0,
          "volume": 1105212.6575348014
        },
        {
          "count": 3,
          "country": "BH",
          "recent": 0,
          "volume": 1666461.7862936694
        },
        {
          "count": 2,
          "country": "VE",
          "recent": 0,
          "volume": 0
        },
        {
          "count": 2,
          "country": "MY",
          "recent": 0,
          "volume": 0
        },
        {
          "count": 2,
          "country": "PK",
          "recent": 0,
          "volume": 440170.7944138581
        },
        {
          "count": 2,
          "country": "ES",
          "recent": 0,
          "volume": 0
        },
        {
          "count": 2,
          "country": "PE",
          "recent": 1,
          "volume": 44528168.43746718
        },
        {
          "count": 2,
          "country": "HU",
          "recent": 0,
          "volume": 22173.739497000002
        },
        {
          "count": 2,
          "country": "KP",
          "recent": 0,
          "volume": 103339.74264399988
        },
        {
          "count": 2,
          "country": "NG",
          "recent": 0,
          "volume": 1859.358137
        },
        {
          "count": 2,
          "country": "AF",
          "recent": 0,
          "volume": 6389715.091197194
        },
        {
          "count": 1,
          "country": "SK",
          "recent": 0,
          "volume": 0
        },
        {
          "count": 1,
          "country": "IT",
          "recent": 1,
          "volume": 11428.19777693
        },
        {
          "count": 1,
          "country": "LV",
          "recent": 0,
          "volume": 0
        },
        {
          "count": 1,
          "country": "LY",
          "recent": 0,
          "volume": 16164422.107059086
        },
        {
          "count": 1,
          "country": "PT",
          "recent": 0,
          "volume": 16002747.327695455
        },
        {
          "count": 1,
          "country": "PH",
          "recent": 0,
          "volume": 171581.13614755982
        },
        {
          "count": 1,
          "country": "TW",
          "recent": 0,
          "volume": 0
        },
        {
          "count": 1,
          "country": "IQ",
          "recent": 0,
          "volume": 16164422.107059086
        },
        {
          "count": 1,
          "country": "GR",
          "recent": 0,
          "volume": 0
        },
        {
          "count": 1,
          "country": "BR",
          "recent": 0,
          "volume": 6140909.853785219
        },
        {
          "count": 1,
          "country": "SI",
          "recent": 0,
          "volume": 133518.08245511004
        },
        {
          "count": 1,
          "country": "HK",
          "recent": 0,
          "volume": 0
        },
        {
          "count": 1,
          "country": "ZA",
          "recent": 0,
          "volume": 0
        },
        {
          "count": 1,
          "country": "DK",
          "recent": 0,
          "volume": 0
        },
        {
          "count": 1,
          "country": "AM",
          "recent": 1,
          "volume": 0
        },
        {
          "count": 1,
          "country": "SY",
          "recent": 0,
          "volume": 0
        }
      ],
      "diamonds": [
        {
          "a": 10890,
          "s": "BUY",
          "t": "\u2191 $200"
        },
        {
          "a": 22385.79327,
          "s": "BUY",
          "t": ""
        },
        {
          "a": 20135.3473,
          "s": "BUY",
          "t": ""
        },
        {
          "a": 11939.78043,
          "s": "SELL",
          "t": "March 31"
        },
        {
          "a": 11626.3,
          "s": "BUY",
          "t": "\u2193 50,000"
        },
        {
          "a": 104299.999998,
          "s": "BUY",
          "t": "64,000"
        },
        {
          "a": 14990.679998,
          "s": "BUY",
          "t": ""
        },
        {
          "a": 14985,
          "s": "BUY",
          "t": "80-99"
        },
        {
          "a": 13880.76378,
          "s": "BUY",
          "t": "March 31"
        },
        {
          "a": 33925.356,
          "s": "BUY",
          "t": "March 31"
        },
        {
          "a": 18796.819998,
          "s": "BUY",
          "t": ""
        },
        {
          "a": 18040.345,
          "s": "SELL",
          "t": ""
        },
        {
          "a": 14568.0073,
          "s": "SELL",
          "t": "March 31"
        },
        {
          "a": 15639.2801,
          "s": "SELL",
          "t": "March 31"
        },
        {
          "a": 18627.6651,
          "s": "BUY",
          "t": "December 31"
        },
        {
          "a": 10012.38696,
          "s": "SELL",
          "t": "March 31"
        },
        {
          "a": 24775,
          "s": "BUY",
          "t": "March 31"
        },
        {
          "a": 11460.3786,
          "s": "BUY",
          "t": "March 31"
        },
        {
          "a": 11413.117,
          "s": "BUY",
          "t": ""
        },
        {
          "a": 18398.57019,
          "s": "BUY",
          "t": ""
        },
        {
          "a": 29978.14769,
          "s": "BUY",
          "t": ""
        },
        {
          "a": 108020,
          "s": "SELL",
          "t": "March 31"
        },
        {
          "a": 14049.88138,
          "s": "SELL",
          "t": "March 31"
        },
        {
          "a": 19385.76026,
          "s": "BUY",
          "t": "\u2191 $150"
        },
        {
          "a": 10313.06661,
          "s": "BUY",
          "t": "March 31"
        },
        {
          "a": 11905.083,
          "s": "BUY",
          "t": "260-279"
        },
        {
          "a": 11913.30465,
          "s": "SELL",
          "t": "80-99"
        },
        {
          "a": 41437.33088,
          "s": "BUY",
          "t": ""
        },
        {
          "a": 10562.4443,
          "s": "SELL",
          "t": ""
        },
        {
          "a": 103066.94034,
          "s": "BUY",
          "t": "March 31"
        }
      ],
      "dots": [
        {
          "c": "US",
          "l": "high"
        },
        {
          "c": "IR",
          "l": "high"
        },
        {
          "c": "US",
          "l": "critical"
        },
        {
          "c": "IR",
          "l": "critical"
        },
        {
          "c": "IR",
          "l": "critical"
        },
        {
          "c": "US",
          "l": "critical"
        },
        {
          "c": "PS",
          "l": "critical"
        },
        {
          "c": "IR",
          "l": "critical"
        },
        {
          "c": "IL",
          "l": "critical"
        },
        {
          "c": "IL",
          "l": "critical"
        },
        {
          "c": "IR",
          "l": "critical"
        },
        {
          "c": "GB",
          "l": "critical"
        },
        {
          "c": "IR",
          "l": "critical"
        },
        {
          "c": "US",
          "l": "critical"
        },
        {
          "c": "IR",
          "l": "critical"
        },
        {
          "c": "GL",
          "l": "critical"
        },
        {
          "c": "IN",
          "l": "critical"
        },
        {
          "c": "IL",
          "l": "critical"
        },
        {
          "c": "IR",
          "l": "critical"
        },
        {
          "c": "IL",
          "l": "critical"
        },
        {
          "c": "IR",
          "l": "critical"
        },
        {
          "c": "IR",
          "l": "critical"
        },
        {
          "c": "IR",
          "l": "critical"
        },
        {
          "c": "US",
          "l": "critical"
        },
        {
          "c": "UA",
          "l": "critical"
        },
        {
          "c": "IL",
          "l": "critical"
        },
        {
          "c": "GB",
          "l": "critical"
        },
        {
          "c": "IR",
          "l": "critical"
        },
        {
          "c": "IR",
          "l": "critical"
        },
        {
          "c": "RU",
          "l": "critical"
        },
        {
          "c": "IR",
          "l": "critical"
        },
        {
          "c": "US",
          "l": "critical"
        },
        {
          "c": "SI",
          "l": "critical"
        },
        {
          "c": "IL",
          "l": "critical"
        },
        {
          "c": "CN",
          "l": "critical"
        },
        {
          "c": "RU",
          "l": "critical"
        },
        {
          "c": "BH",
          "l": "critical"
        },
        {
          "c": "GB",
          "l": "critical"
        },
        {
          "c": "IL",
          "l": "critical"
        },
        {
          "c": "DE",
          "l": "critical"
        },
        {
          "c": "IL",
          "l": "critical"
        },
        {
          "c": "IR",
          "l": "critical"
        },
        {
          "c": "IR",
          "l": "critical"
        },
        {
          "c": "IL",
          "l": "critical"
        },
        {
          "c": "IL",
          "l": "critical"
        },
        {
          "c": "US",
          "l": "critical"
        },
        {
          "c": "IR",
          "l": "critical"
        },
        {
          "c": "IR",
          "l": "critical"
        },
        {
          "c": "IR",
          "l": "critical"
        },
        {
          "c": "IL",
          "l": "critical"
        }
      ],
      "flights": [
        {
          "cat": "Presidential",
          "cs": "CTM1275",
          "lat": 49.0728,
          "lng": 1.2769,
          "ts": 1773997030487
        },
        {
          "cat": "AWACS",
          "cs": "NATO01",
          "lat": 63.6184,
          "lng": 9.5741,
          "ts": 1773996052042
        },
        {
          "cat": "Heavy Cargo",
          "cs": "BGA113G",
          "lat": 48.5274,
          "lng": 8.6798,
          "ts": 1773994977408
        },
        {
          "cat": "Presidential",
          "cs": "RSD930",
          "lat": 55.9821,
          "lng": 37.4164,
          "ts": 1773993526616
        },
        {
          "cat": "AWACS",
          "cs": "WGTL27",
          "lat": -32.8087,
          "lng": 151.8531,
          "ts": 1773983805679
        },
        {
          "cat": "Royal",
          "cs": "N/A",
          "lat": 25.5515,
          "lng": 55.3814,
          "ts": 1773982216983
        }
      ],
      "_scraped_at": "2026-03-20T09:04:24.790431+00:00",
      "_source": "api",
      "_source_api_url": "https://api-v2.glint.trade/api/public/globe"
    }
  ]
}